evaldb/__init__.py
evaldb-0.0.2.dist-info/LICENSE
evaldb-0.0.2.dist-info/METADATA
evaldb-0.0.2.dist-info/WHEEL
evaldb-0.0.2.dist-info/top_level.txt
evaldb-0.0.2.dist-info/RECORD
