Metadata-Version: 2.1
Name: evaldb
Version: 0.0.2
Summary: Python client for evaldb (evaldb.turb.io).
Home-page: https://github.com/turbio/evaldb
Author: Mason Clayton
Author-email: mason@turb.io
License: UNKNOWN
Platform: UNKNOWN
Classifier: Programming Language :: Python :: 3
Classifier: License :: OSI Approved :: MIT License
Classifier: Operating System :: OS Independent
Requires-Python: >=3.6
